{
  "routes": [
    {
      "method": "GET",
      "path": "/hogars",
      "handler": "hogar.find",
      "config": {
        "policies": []
      }
    },
    {
      "method": "GET",
      "path": "/hogars/count",
      "handler": "hogar.count",
      "config": {
        "policies": []
      }
    },
    {
      "method": "GET",
      "path": "/hogars/:id",
      "handler": "hogar.findOne",
      "config": {
        "policies": []
      }
    },
    {
      "method": "POST",
      "path": "/hogars",
      "handler": "hogar.create",
      "config": {
        "policies": []
      }
    },
    {
      "method": "PUT",
      "path": "/hogars/:id",
      "handler": "hogar.update",
      "config": {
        "policies": []
      }
    },
    {
      "method": "DELETE",
      "path": "/hogars/:id",
      "handler": "hogar.delete",
      "config": {
        "policies": []
      }
    }
  ]
}
